fhirpy/__init__.py
fhirpy/lib.py
fhirpy/py.typed
fhirpy/base/__init__.py
fhirpy/base/client.py
fhirpy/base/exceptions.py
fhirpy/base/lib_async.py
fhirpy/base/lib_sync.py
fhirpy/base/resource.py
fhirpy/base/resource_protocol.py
fhirpy/base/searchset.py
fhirpy/base/utils.py
fhirpy-2.2.0.dist-info/licenses/LICENSE.md
fhirpy-2.2.0.dist-info/WHEEL
fhirpy-2.2.0.dist-info/METADATA
fhirpy-2.2.0.dist-info/RECORD
