Metadata-Version: 2.4
Name: fhirpy
Version: 2.2.0
Summary: FHIR client for python
Keywords: fhir
Author-email: "beda.software" <fhirpy@beda.software>
Requires-Python: >=3.9
Classifier: Development Status :: 5 - Production/Stable
Classifier: Environment :: Web Environment
Classifier: Intended Audience :: Developers
Classifier: Operating System :: OS Independent
Classifier: Programming Language :: Python
Classifier: Programming Language :: Python :: 3
Classifier: Programming Language :: Python :: 3.9
Classifier: Programming Language :: Python :: 3.10
Classifier: Programming Language :: Python :: 3.11
Classifier: Programming Language :: Python :: 3.12
Classifier: Topic :: Internet :: WWW/HTTP
Classifier: Topic :: Software Development :: Libraries :: Python Modules
License-File: LICENSE.md
Requires-Dist: requests>=2.25.1
Requires-Dist: aiohttp>=3.6.3
Requires-Dist: pytz
Requires-Dist: typing-extensions
Requires-Dist: pytest>=6.2.4 ; extra == "test"
Requires-Dist: pytest-asyncio>=0.15.1 ; extra == "test"
Requires-Dist: responses>=0.13.3 ; extra == "test"
Project-URL: Documentation, https://github.com/beda-software/fhir-py#readme
Project-URL: Homepage, https://github.com/beda-software/fhir-py
Project-URL: Source, https://github.com/beda-software/fhir-py.git
Provides-Extra: test
